{
  "date": "2026-07-03",
  "generated_at": "2026-07-03T05:43:36.695962+00:00",
  "methodology_version": "1.0",
  "stablecoin_stress": {
    "total_stablecoin_mcap_usd_bn": 268.85,
    "system_peg_stress_index": 0.092332,
    "system_stress_level": "NORMAL",
    "critical_count": 0,
    "warning_count": 1,
    "coins": [
      {
        "id": "frax",
        "symbol": "FRAX",
        "name": "Legacy Frax Dollar",
        "price_usd": 0.989427,
        "peg_deviation": -0.010573,
        "peg_deviation_pct": 1.0573,
        "status": "WARNING",
        "market_cap_usd_bn": 0.237,
        "volume_24h_usd_bn": 0.002,
        "price_change_24h_pct": -0.108
      },
      {
        "id": "first-digital-usd",
        "symbol": "FDUSD",
        "name": "First Digital USD",
        "price_usd": 0.996719,
        "peg_deviation": -0.003281,
        "peg_deviation_pct": 0.3281,
        "status": "STABLE",
        "market_cap_usd_bn": 0.349,
        "volume_24h_usd_bn": 0.038,
        "price_change_24h_pct": -0.0127
      },
      {
        "id": "true-usd",
        "symbol": "TUSD",
        "name": "TrueUSD",
        "price_usd": 0.997712,
        "peg_deviation": -0.002288,
        "peg_deviation_pct": 0.2288,
        "status": "STABLE",
        "market_cap_usd_bn": 0.493,
        "volume_24h_usd_bn": 0.019,
        "price_change_24h_pct": -0.0267
      },
      {
        "id": "ethena-usde",
        "symbol": "USDE",
        "name": "Ethena USDe",
        "price_usd": 0.998511,
        "peg_deviation": -0.001489,
        "peg_deviation_pct": 0.1489,
        "status": "STABLE",
        "market_cap_usd_bn": 4.445,
        "volume_24h_usd_bn": 0.094,
        "price_change_24h_pct": 0.0017
      },
      {
        "id": "usdd",
        "symbol": "USDD",
        "name": "USDD",
        "price_usd": 0.998695,
        "peg_deviation": -0.001305,
        "peg_deviation_pct": 0.1305,
        "status": "STABLE",
        "market_cap_usd_bn": 1.388,
        "volume_24h_usd_bn": 0.003,
        "price_change_24h_pct": -0.0371
      },
      {
        "id": "tether",
        "symbol": "USDT",
        "name": "Tether",
        "price_usd": 0.998822,
        "peg_deviation": -0.001178,
        "peg_deviation_pct": 0.1178,
        "status": "STABLE",
        "market_cap_usd_bn": 184.073,
        "volume_24h_usd_bn": 59.139,
        "price_change_24h_pct": 0.0094
      },
      {
        "id": "dai",
        "symbol": "DAI",
        "name": "Dai",
        "price_usd": 0.99963,
        "peg_deviation": -0.00037,
        "peg_deviation_pct": 0.037,
        "status": "STABLE",
        "market_cap_usd_bn": 4.623,
        "volume_24h_usd_bn": 0.191,
        "price_change_24h_pct": -0.018
      },
      {
        "id": "paxos-standard",
        "symbol": "USDP",
        "name": "Pax Dollar",
        "price_usd": 0.999735,
        "peg_deviation": -0.000265,
        "peg_deviation_pct": 0.0265,
        "status": "STABLE",
        "market_cap_usd_bn": 0.032,
        "volume_24h_usd_bn": 0.007,
        "price_change_24h_pct": 0.072
      },
      {
        "id": "usd-coin",
        "symbol": "USDC",
        "name": "USDC",
        "price_usd": 0.999775,
        "peg_deviation": -0.000225,
        "peg_deviation_pct": 0.0225,
        "status": "STABLE",
        "market_cap_usd_bn": 73.215,
        "volume_24h_usd_bn": 12.678,
        "price_change_24h_pct": 0.0079
      }
    ]
  },
  "protocol_leverage": {
    "system_leverage_index": 0.0,
    "system_leverage_pct": 0.0,
    "system_stress_level": "LOW",
    "total_lending_tvl_usd_bn": 24.59,
    "protocols": [
      {
        "protocol": "morpho-blue",
        "tvl_usd_bn": 9.969,
        "total_borrow_usd_bn": 0.0,
        "utilization": 0.0,
        "utilization_pct": 0.0,
        "stress_level": "LOW",
        "avg_borrow_apy_pct": 0.0,
        "pool_count": 620
      },
      {
        "protocol": "aave-v3",
        "tvl_usd_bn": 13.466,
        "total_borrow_usd_bn": 0.0,
        "utilization": 0.0,
        "utilization_pct": 0.0,
        "stress_level": "LOW",
        "avg_borrow_apy_pct": 0.0,
        "pool_count": 219
      },
      {
        "protocol": "compound-v3",
        "tvl_usd_bn": 1.073,
        "total_borrow_usd_bn": 0.0,
        "utilization": 0.0,
        "utilization_pct": 0.0,
        "stress_level": "LOW",
        "avg_borrow_apy_pct": 0.0,
        "pool_count": 105
      },
      {
        "protocol": "compound-v2",
        "tvl_usd_bn": 0.086,
        "total_borrow_usd_bn": 0.0,
        "utilization": 0.0,
        "utilization_pct": 0.0,
        "stress_level": "LOW",
        "avg_borrow_apy_pct": 0.0,
        "pool_count": 14
      }
    ]
  },
  "bridge_risk": {},
  "liquidation_cascade": {
    "method": "TVL-proxy (no Graph data)",
    "lending_tvl_usd_bn": 36.56,
    "avg_ltv_assumption": 0.7,
    "scenarios": {
      "drop_10pct": {
        "estimated_liquidatable_usd_bn": 5.22
      },
      "drop_20pct": {
        "estimated_liquidatable_usd_bn": 10.45
      },
      "drop_30pct": {
        "estimated_liquidatable_usd_bn": 15.67
      },
      "drop_40pct": {
        "estimated_liquidatable_usd_bn": 20.89
      },
      "drop_50pct": {
        "estimated_liquidatable_usd_bn": 26.11
      }
    }
  },
  "onchain_stress": {
    "btc": {
      "exchange_balance": null,
      "mvrv_z_score": null,
      "sopr": null,
      "tx_count": null,
      "price_usd": null
    },
    "eth": {
      "exchange_balance": null,
      "mvrv_z_score": null,
      "sopr": null,
      "tx_count": null,
      "price_usd": null
    }
  },
  "defi_global": {
    "defi_market_cap": "92815504956.41759829591157482206",
    "eth_market_cap": "206568840159.06029113427289438048",
    "defi_to_eth_ratio": "44.9319969483048039275891471929742486944919176202277067659892929339256696",
    "trading_volume_24h": "3129154750.4790298093999828146996",
    "defi_dominance": "4.1823208256153823685916965952009025975472195719650476013792201936963726",
    "top_coin_name": "Lido Staked Ether",
    "top_coin_defi_dominance": 16.863276560262246
  },
  "top_chains_tvl": [
    {
      "chain": "Ethereum",
      "tvl_usd_bn": 38.98
    },
    {
      "chain": "Solana",
      "tvl_usd_bn": 5.04
    },
    {
      "chain": "BSC",
      "tvl_usd_bn": 4.92
    },
    {
      "chain": "Tron",
      "tvl_usd_bn": 4.47
    },
    {
      "chain": "Base",
      "tvl_usd_bn": 4.28
    },
    {
      "chain": "Bitcoin",
      "tvl_usd_bn": 4.02
    },
    {
      "chain": "Hyperliquid L1",
      "tvl_usd_bn": 1.44
    },
    {
      "chain": "Provenance",
      "tvl_usd_bn": 1.4
    },
    {
      "chain": "Arbitrum",
      "tvl_usd_bn": 1.23
    },
    {
      "chain": "Polygon",
      "tvl_usd_bn": 0.92
    }
  ]
}