{
  "date": "2026-04-04",
  "generated_at": "2026-04-04T04:07:49.069190+00:00",
  "methodology_version": "1.0",
  "stablecoin_stress": {
    "total_stablecoin_mcap_usd_bn": 274.77,
    "system_peg_stress_index": 0.010632,
    "system_stress_level": "NORMAL",
    "critical_count": 0,
    "warning_count": 1,
    "coins": [
      {
        "id": "frax",
        "symbol": "FRAX",
        "name": "Legacy Frax Dollar",
        "price_usd": 0.993202,
        "peg_deviation": -0.006798,
        "peg_deviation_pct": 0.6798,
        "status": "WARNING",
        "market_cap_usd_bn": 0.274,
        "volume_24h_usd_bn": 0.004,
        "price_change_24h_pct": 0.2568
      },
      {
        "id": "first-digital-usd",
        "symbol": "FDUSD",
        "name": "First Digital USD",
        "price_usd": 0.999003,
        "peg_deviation": -0.000997,
        "peg_deviation_pct": 0.0997,
        "status": "STABLE",
        "market_cap_usd_bn": 0.394,
        "volume_24h_usd_bn": 0.068,
        "price_change_24h_pct": -0.0129
      },
      {
        "id": "paxos-standard",
        "symbol": "USDP",
        "name": "Pax Dollar",
        "price_usd": 0.999721,
        "peg_deviation": -0.000279,
        "peg_deviation_pct": 0.0279,
        "status": "STABLE",
        "market_cap_usd_bn": 0.041,
        "volume_24h_usd_bn": 0.007,
        "price_change_24h_pct": -0.005
      },
      {
        "id": "ethena-usde",
        "symbol": "USDE",
        "name": "Ethena USDe",
        "price_usd": 0.999736,
        "peg_deviation": -0.000264,
        "peg_deviation_pct": 0.0264,
        "status": "STABLE",
        "market_cap_usd_bn": 5.888,
        "volume_24h_usd_bn": 0.147,
        "price_change_24h_pct": 0.0167
      },
      {
        "id": "true-usd",
        "symbol": "TUSD",
        "name": "TrueUSD",
        "price_usd": 0.999813,
        "peg_deviation": -0.000187,
        "peg_deviation_pct": 0.0187,
        "status": "STABLE",
        "market_cap_usd_bn": 0.494,
        "volume_24h_usd_bn": 0.011,
        "price_change_24h_pct": 0.0821
      },
      {
        "id": "tether",
        "symbol": "USDT",
        "name": "Tether",
        "price_usd": 0.999865,
        "peg_deviation": -0.000135,
        "peg_deviation_pct": 0.0135,
        "status": "STABLE",
        "market_cap_usd_bn": 184.147,
        "volume_24h_usd_bn": 36.113,
        "price_change_24h_pct": -0.0034
      },
      {
        "id": "dai",
        "symbol": "DAI",
        "name": "Dai",
        "price_usd": 0.999901,
        "peg_deviation": -9.9e-05,
        "peg_deviation_pct": 0.0099,
        "status": "STABLE",
        "market_cap_usd_bn": 4.452,
        "volume_24h_usd_bn": 0.198,
        "price_change_24h_pct": -0.0095
      },
      {
        "id": "usd-coin",
        "symbol": "USDC",
        "name": "USDC",
        "price_usd": 1.0,
        "peg_deviation": 0.0,
        "peg_deviation_pct": 0.0,
        "status": "STABLE",
        "market_cap_usd_bn": 77.53,
        "volume_24h_usd_bn": 5.8,
        "price_change_24h_pct": 0.0041
      },
      {
        "id": "usdd",
        "symbol": "USDD",
        "name": "USDD",
        "price_usd": 1.0,
        "peg_deviation": 0.0,
        "peg_deviation_pct": 0.0,
        "status": "STABLE",
        "market_cap_usd_bn": 1.552,
        "volume_24h_usd_bn": 0.005,
        "price_change_24h_pct": 0.0136
      }
    ]
  },
  "protocol_leverage": {
    "system_leverage_index": 0.0,
    "system_leverage_pct": 0.0,
    "system_stress_level": "LOW",
    "total_lending_tvl_usd_bn": 26.65,
    "protocols": [
      {
        "protocol": "aave-v3",
        "tvl_usd_bn": 25.341,
        "total_borrow_usd_bn": 0.0,
        "utilization": 0.0,
        "utilization_pct": 0.0,
        "stress_level": "LOW",
        "avg_borrow_apy_pct": 0.0,
        "pool_count": 205
      },
      {
        "protocol": "compound-v3",
        "tvl_usd_bn": 1.2,
        "total_borrow_usd_bn": 0.0,
        "utilization": 0.0,
        "utilization_pct": 0.0,
        "stress_level": "LOW",
        "avg_borrow_apy_pct": 0.0,
        "pool_count": 108
      },
      {
        "protocol": "compound-v2",
        "tvl_usd_bn": 0.111,
        "total_borrow_usd_bn": 0.0,
        "utilization": 0.0,
        "utilization_pct": 0.0,
        "stress_level": "LOW",
        "avg_borrow_apy_pct": 0.0,
        "pool_count": 14
      },
      {
        "protocol": "radiant-v2",
        "tvl_usd_bn": 0.002,
        "total_borrow_usd_bn": 0.0,
        "utilization": 0.0,
        "utilization_pct": 0.0,
        "stress_level": "LOW",
        "avg_borrow_apy_pct": 0.0,
        "pool_count": 36
      }
    ]
  },
  "bridge_risk": {},
  "liquidation_cascade": {
    "method": "TVL-proxy (no Graph data)",
    "lending_tvl_usd_bn": 47.81,
    "avg_ltv_assumption": 0.7,
    "scenarios": {
      "drop_10pct": {
        "estimated_liquidatable_usd_bn": 6.83
      },
      "drop_20pct": {
        "estimated_liquidatable_usd_bn": 13.66
      },
      "drop_30pct": {
        "estimated_liquidatable_usd_bn": 20.49
      },
      "drop_40pct": {
        "estimated_liquidatable_usd_bn": 27.32
      },
      "drop_50pct": {
        "estimated_liquidatable_usd_bn": 34.15
      }
    }
  },
  "onchain_stress": {
    "btc": {
      "exchange_balance": null,
      "mvrv_z_score": null,
      "sopr": null,
      "tx_count": null,
      "price_usd": null
    },
    "eth": {
      "exchange_balance": null,
      "mvrv_z_score": null,
      "sopr": null,
      "tx_count": null,
      "price_usd": null
    }
  },
  "defi_global": {
    "defi_market_cap": "79113141625.27496415787882862592",
    "eth_market_cap": "247374788329.02843325594278068664",
    "defi_to_eth_ratio": "31.9810851217578813421800490991657513432893030169201744586809406421986841",
    "trading_volume_24h": "2200971354.1375460926952834792976",
    "defi_dominance": "3.3198387182266257906229074258050588647753183066905436647313274951084596",
    "top_coin_name": "Lido Staked Ether",
    "top_coin_defi_dominance": 24.027377668552397
  },
  "top_chains_tvl": [
    {
      "chain": "Ethereum",
      "tvl_usd_bn": 52.78
    },
    {
      "chain": "Solana",
      "tvl_usd_bn": 5.44
    },
    {
      "chain": "BSC",
      "tvl_usd_bn": 5.36
    },
    {
      "chain": "Tron",
      "tvl_usd_bn": 4.81
    },
    {
      "chain": "Bitcoin",
      "tvl_usd_bn": 4.53
    },
    {
      "chain": "Base",
      "tvl_usd_bn": 4.05
    },
    {
      "chain": "Arbitrum",
      "tvl_usd_bn": 1.89
    },
    {
      "chain": "Hyperliquid L1",
      "tvl_usd_bn": 1.61
    },
    {
      "chain": "Provenance",
      "tvl_usd_bn": 1.58
    },
    {
      "chain": "Plasma",
      "tvl_usd_bn": 1.58
    }
  ]
}